jx_base/__init__.py
jx_base/data_class.py
jx_base/domains.py
jx_base/language.py
jx_base/meta_columns.py
jx_base/queries.py
jx_base/utils.py
jx_base/expressions/__init__.py
jx_base/expressions/_utils.py
jx_base/expressions/abs_op.py
jx_base/expressions/add_op.py
jx_base/expressions/aggregate_op.py
jx_base/expressions/all_op.py
jx_base/expressions/and_op.py
jx_base/expressions/any_op.py
jx_base/expressions/array_of_op.py
jx_base/expressions/avg_op.py
jx_base/expressions/base_binary_op.py
jx_base/expressions/base_inequality_op.py
jx_base/expressions/base_multi_op.py
jx_base/expressions/between_op.py
jx_base/expressions/call_op.py
jx_base/expressions/cardinality_op.py
jx_base/expressions/case_op.py
jx_base/expressions/coalesce_op.py
jx_base/expressions/comment_op.py
jx_base/expressions/concat_op.py
jx_base/expressions/count_op.py
jx_base/expressions/date_op.py
jx_base/expressions/default_op.py
jx_base/expressions/div_op.py
jx_base/expressions/eq_op.py
jx_base/expressions/es_script.py
jx_base/expressions/es_select_op.py
jx_base/expressions/exists_op.py
jx_base/expressions/exp_op.py
jx_base/expressions/expression.py
jx_base/expressions/false_op.py
jx_base/expressions/filter_op.py
jx_base/expressions/find_op.py
jx_base/expressions/first_op.py
jx_base/expressions/floor_op.py
jx_base/expressions/format_op.py
jx_base/expressions/from_op.py
jx_base/expressions/from_unix_op.py
jx_base/expressions/get_op.py
jx_base/expressions/group_op.py
jx_base/expressions/gt_op.py
jx_base/expressions/gte_op.py
jx_base/expressions/in_op.py
jx_base/expressions/inner_join_op.py
jx_base/expressions/is_boolean_op.py
jx_base/expressions/is_integer_op.py
jx_base/expressions/is_number_op.py
jx_base/expressions/is_text_op.py
jx_base/expressions/last_op.py
jx_base/expressions/least_op.py
jx_base/expressions/leaves_op.py
jx_base/expressions/left_op.py
jx_base/expressions/length_op.py
jx_base/expressions/limit_op.py
jx_base/expressions/literal.py
jx_base/expressions/lt_op.py
jx_python-4.673.25037.dist-info/LICENSE
jx_python-4.673.25037.dist-info/METADATA
jx_python-4.673.25037.dist-info/WHEEL
jx_python-4.673.25037.dist-info/top_level.txt
jx_python-4.673.25037.dist-info/RECORD
