Metadata-Version: 2.2
Name: jx-python
Version: 4.673.25037
Summary: JSON query expressions using Python
Home-page: https://github.com/klahnakoski/jx-python
Author: Kyle Lahnakoski
Author-email: kyle@lahnakoski.com
License: MPL 2.0
Classifier: Development Status :: 4 - Beta
Classifier: Topic :: Software Development :: Libraries
Classifier: Topic :: Software Development :: Libraries :: Python Modules
Classifier: License :: OSI Approved :: Mozilla Public License 2.0 (MPL 2.0)
Classifier: Programming Language :: Python :: 3.8
Classifier: Programming Language :: Python :: 3.9
Classifier: Programming Language :: Python :: 3.11
Classifier: Programming Language :: Python :: 3.12
Classifier: Programming Language :: Python :: 3.13
License-File: LICENSE
Requires-Dist: mo-collections==5.672.25036
Requires-Dist: mo-dots==10.672.25036
Requires-Dist: mo-future==7.672.25036
Requires-Dist: mo-json==6.672.25036
Requires-Dist: mo-json-config==4.673.25037
Requires-Dist: mo-kwargs==7.672.25036
Requires-Dist: mo-logs==8.672.25036
Requires-Dist: mo-math==7.672.25036
Requires-Dist: mo-threads==6.672.25036
Requires-Dist: mo-times==5.672.25036
Provides-Extra: tests
Requires-Dist: mo-testing>=8.623.24125; extra == "tests"
Dynamic: author
Dynamic: author-email
Dynamic: classifier
Dynamic: description
Dynamic: description-content-type
Dynamic: home-page
Dynamic: license
Dynamic: provides-extra
Dynamic: requires-dist
Dynamic: summary
